.gitignore
.travis.yml
CHANGELOG.rst
LICENSE
MANIFEST.in
README.rst
readthedocs.yml
setup.py
docrep/__init__.py
docrep/decorators.py
docrep.egg-info/PKG-INFO
docrep.egg-info/SOURCES.txt
docrep.egg-info/dependency_links.txt
docrep.egg-info/not-zip-safe
docrep.egg-info/requires.txt
docrep.egg-info/top_level.txt
docs/Makefile
docs/conf.py
docs/environment.yml
docs/index.rst
docs/requirements.txt
tests/test_docrep.py