Metadata-Version: 2.1
Name: docrep
Version: 0.3.2
Summary: Python package for docstring repetition
Home-page: https://github.com/Chilipp/docrep
Author: Philipp S. Sommer
Author-email: philipp.sommer@hzg.de
License: Apache-2.0
Project-URL: Documentation, https://docrep.readthedocs.io
Project-URL: Source, https://github.com/Chilipp/docrep
Project-URL: Tracker, https://github.com/Chilipp/docrep/issues
Keywords: docstrings docs docstring napoleon numpy reStructured text
Platform: UNKNOWN
Classifier: Development Status :: 5 - Production/Stable
Classifier: Intended Audience :: Developers
Classifier: Topic :: Documentation
Classifier: License :: OSI Approved :: Apache Software License
Classifier: Programming Language :: Python :: 2
Classifier: Programming Language :: Python :: 2.7
Classifier: Programming Language :: Python :: 3
Classifier: Programming Language :: Python :: 3.4
Classifier: Programming Language :: Python :: 3.5
Classifier: Programming Language :: Python :: 3.6
Classifier: Programming Language :: Python :: 3.7
Classifier: Programming Language :: Python :: 3.8
Classifier: Programming Language :: Python :: 3.9
Classifier: Operating System :: OS Independent
